specify/__init__.py
specify/__main__.py
specify/builtin_matchers.py
specify/exceptions.py
specify/mocking_decorator.py
specify/object_behavior.py
specify/result.py
specify/runner.py
specify/spec_finder.py
specify/subject.py
specify/utils.py
specify-0.0.9.dist-info/LICENSE
specify-0.0.9.dist-info/WHEEL
specify-0.0.9.dist-info/METADATA
specify-0.0.9.dist-info/RECORD
